{"codigo":30102,"razao":"NATON - IND. COM. E IMP. E EXPORTACAO LTDA.","fantasia":"NATON - LOJA DO VENDEDOR","cnpj":"19.778.894/0001-73","cpf":null,"endereco":{"logradouro":"AV. MONTE SINAI N.35","complemento":"QD 08 LT 01","fone":"3338-1708","celular":null},"bairro":{"nome":"RESIDENCIAL MONTE SINAI"},"atividades":[{"subclasse":"4772-5/00","tipo":"Principal","atividade":"Comercio varejista de cosmeticos, produtos de perfumaria e de higiene pessoal","equipe":"CS","complexidade":"BAIXA"}],"alvara_ultimo":{"dt_validade":"2021-02-24","exercicio":2020},"inspecoes":[{"ndoc":89494,"dt_visita":"2023-05-29","tipo":"MANIFESTAÇÃO DO FISCAL ATUANTE","numer":"000001","Fiscal1":"FABÍOLA PEDROSA PEIXOTO MARQUES","Fiscal2":"THIAGO GOMES GOBO","Fiscal3":null,"pz_retorno":0},{"ndoc":87297,"dt_visita":"2023-03-01","tipo":"AUTO DE INFRAÇÃO","numer":"002999","Fiscal1":"FABÍOLA PEDROSA PEIXOTO MARQUES","Fiscal2":"LUCIANA SANTANA DA ROCHA","Fiscal3":"KAMILLA CHRYSTINE ROLIM D. SANTOS GARCÊS","pz_retorno":0},{"ndoc":87296,"dt_visita":"2023-03-01","tipo":"AUTO DE IMPOSIÇÃO DE PENALIDADE","numer":"096875","Fiscal1":"FABÍOLA PEDROSA PEIXOTO MARQUES","Fiscal2":"THIAGO GOMES GOBO","Fiscal3":"KAMILLA CHRYSTINE ROLIM D. SANTOS GARCÊS","pz_retorno":0},{"ndoc":70000,"dt_visita":"2021-02-02","tipo":"ATO ADMINISTRATIVO DA GERÊNCIA","numer":"08706","Fiscal1":"JULIO CÉSAR TELES SPINDOLA","Fiscal2":null,"Fiscal3":null,"pz_retorno":30},{"ndoc":69860,"dt_visita":"2021-01-25","tipo":"ATO ADMINISTRATIVO DA GERÊNCIA","numer":"80501","Fiscal1":"JULIO CÉSAR TELES SPINDOLA","Fiscal2":null,"Fiscal3":null,"pz_retorno":30},{"ndoc":64543,"dt_visita":"2020-02-12","tipo":"TERMO DE NOTIFICAÇÃO","numer":"79111","Fiscal1":"PATRÍCIA CORDEIRO DE MORAES E SOUZA","Fiscal2":"LUCIANA SANTANA DA ROCHA","Fiscal3":null,"pz_retorno":0},{"ndoc":64542,"dt_visita":"2020-02-12","tipo":"TERMO DE INTIMAÇÃO","numer":"79110","Fiscal1":"PATRÍCIA CORDEIRO DE MORAES E SOUZA","Fiscal2":"LUCIANA SANTANA DA ROCHA","Fiscal3":null,"pz_retorno":10},{"ndoc":64627,"dt_visita":"2020-02-10","tipo":"TERMO DE INTIMAÇÃO","numer":"76916","Fiscal1":"PATRÍCIA CORDEIRO DE MORAES E SOUZA","Fiscal2":"LUCIANA SANTANA DA ROCHA","Fiscal3":null,"pz_retorno":30},{"ndoc":64630,"dt_visita":"2020-02-08","tipo":"AUTO DE IMPOSIÇÃO DE PENALIDADE","numer":"74649","Fiscal1":"PATRÍCIA CORDEIRO DE MORAES E SOUZA","Fiscal2":"LUCIANA SANTANA DA ROCHA","Fiscal3":null,"pz_retorno":0},{"ndoc":64013,"dt_visita":"2020-01-22","tipo":"TERMO DE COLETA DE AMOSTRA","numer":"11460","Fiscal1":"PATRÍCIA CORDEIRO DE MORAES E SOUZA","Fiscal2":"LUCIANA SANTANA DA ROCHA","Fiscal3":null,"pz_retorno":0},{"ndoc":64015,"dt_visita":"2020-01-22","tipo":"TERMO DE COLETA DE AMOSTRA","numer":"11461","Fiscal1":"PATRÍCIA CORDEIRO DE MORAES E SOUZA","Fiscal2":"LUCIANA SANTANA DA ROCHA","Fiscal3":null,"pz_retorno":0},{"ndoc":64016,"dt_visita":"2020-01-22","tipo":"TERMO DE COLETA DE AMOSTRA","numer":"11462","Fiscal1":"PATRÍCIA CORDEIRO DE MORAES E SOUZA","Fiscal2":"LUCIANA SANTANA DA ROCHA","Fiscal3":null,"pz_retorno":0},{"ndoc":64012,"dt_visita":"2020-01-22","tipo":"AUTO DE INFRAÇÃO","numer":"01581","Fiscal1":"PATRÍCIA CORDEIRO DE MORAES E SOUZA","Fiscal2":"LUCIANA SANTANA DA ROCHA","Fiscal3":null,"pz_retorno":15},{"ndoc":62240,"dt_visita":"2019-11-04","tipo":"AUTO DE IMPOSIÇÃO DE PENALIDADE","numer":"77181","Fiscal1":"EDUARDO LUCAS M. CASTRO","Fiscal2":null,"Fiscal3":null,"pz_retorno":0},{"ndoc":62237,"dt_visita":"2019-11-04","tipo":"AUTO DE INFRAÇÃO","numer":"03639","Fiscal1":"EDUARDO LUCAS M. CASTRO","Fiscal2":null,"Fiscal3":null,"pz_retorno":0},{"ndoc":61562,"dt_visita":"2019-10-08","tipo":"ATO ADMINISTRATIVO DA GERÊNCIA","numer":"02276","Fiscal1":"JULIO CÉSAR TELES SPINDOLA","Fiscal2":null,"Fiscal3":null,"pz_retorno":0},{"ndoc":61396,"dt_visita":"2019-10-03","tipo":"TERMO DE NOTIFICAÇÃO","numer":"76140","Fiscal1":"TATHIANE PESSOA DE SOUZA","Fiscal2":"JULIANA KÊNIA MARTINS DA SILVA","Fiscal3":null,"pz_retorno":0},{"ndoc":61136,"dt_visita":"2019-09-25","tipo":"TERMO DE INTIMAÇÃO","numer":"75665","Fiscal1":"WANESSA DE BRITO JORGE","Fiscal2":"ADRIANE PEREIRA GUIMARÃES","Fiscal3":null,"pz_retorno":10},{"ndoc":59695,"dt_visita":"2019-07-23","tipo":"TERMO DE INTIMAÇÃO","numer":"74884","Fiscal1":"TATHIANE PESSOA DE SOUZA","Fiscal2":"ADRIANE PEREIRA GUIMARÃES","Fiscal3":null,"pz_retorno":10},{"ndoc":59696,"dt_visita":"2019-07-23","tipo":"AUTO DE IMPOSIÇÃO DE PENALIDADE","numer":"74885","Fiscal1":"TATHIANE PESSOA DE SOUZA","Fiscal2":"ADRIANE PEREIRA GUIMARÃES","Fiscal3":null,"pz_retorno":0},{"ndoc":59727,"dt_visita":"2019-07-23","tipo":"AUTO DE INFRAÇÃO","numer":"02276","Fiscal1":"TATHIANE PESSOA DE SOUZA","Fiscal2":"ADRIANE PEREIRA GUIMARÃES","Fiscal3":null,"pz_retorno":0}]}