{"codigo":15717,"razao":"ATLANTICA CONSTRUCOES COMERCIO E SERVICOS LTDA","fantasia":"TERMINAL RODOVIARIO","cnpj":"00.844.138/0002-58","cpf":null,"endereco":{"logradouro":"AV. BRASIL NORTE","complemento":"Nº 740 SALA 25","fone":"3327-1673","celular":null},"bairro":{"nome":"BAIRRO CIDADE JARDIM"},"atividades":[{"subclasse":"5222-2/00","tipo":"Principal","atividade":"Terminais rodoviarios e ferroviarios","equipe":"AM","complexidade":"MÉDIA"},{"subclasse":"8121-4/00","tipo":"Secundária","atividade":"Limpeza em predios e em domicilios","equipe":"AM","complexidade":"BAIXA"},{"subclasse":"8129-0/00","tipo":"Secundária","atividade":"Atividades de limpeza nao especificadas anteriormente","equipe":"AM","complexidade":"BAIXA"}],"alvara_ultimo":null,"inspecoes":[{"ndoc":96815,"dt_visita":"2024-02-07","tipo":"TERMO DE NOTIFICAÇÃO","numer":"107555","Fiscal1":"PEDRO HENRIQUE AIRES RIBEIRO","Fiscal2":"VANESSA SANTANA","Fiscal3":null,"pz_retorno":0},{"ndoc":84523,"dt_visita":"2022-11-21","tipo":"TERMO DE INTIMAÇÃO","numer":"96221","Fiscal1":"WANESSA DE BRITO JORGE","Fiscal2":"ACADIA DE SOUZA VIEIRA SILVA","Fiscal3":null,"pz_retorno":45},{"ndoc":83369,"dt_visita":"2022-09-30","tipo":"PRORROGAÇÃO","numer":"91980","Fiscal1":"SIMONE DUARTE GROSSI","Fiscal2":"FABÍOLA PEDROSA PEIXOTO MARQUES","Fiscal3":null,"pz_retorno":30},{"ndoc":80723,"dt_visita":"2022-07-01","tipo":"PRORROGAÇÃO","numer":"91980","Fiscal1":"VIVIANE MIYADA","Fiscal2":null,"Fiscal3":null,"pz_retorno":45},{"ndoc":79051,"dt_visita":"2022-05-02","tipo":"PRORROGAÇÃO","numer":"91980","Fiscal1":"ACADIA DE SOUZA VIEIRA SILVA","Fiscal2":null,"Fiscal3":null,"pz_retorno":0},{"ndoc":77823,"dt_visita":"2022-03-17","tipo":"TERMO DE INTIMAÇÃO","numer":"91980","Fiscal1":"ACADIA DE SOUZA VIEIRA SILVA","Fiscal2":"WANESSA DE BRITO JORGE","Fiscal3":null,"pz_retorno":45},{"ndoc":77178,"dt_visita":"2022-02-24","tipo":"TERMO DE INTIMAÇÃO","numer":"91334","Fiscal1":"WANESSA DE BRITO JORGE","Fiscal2":"ACADIA DE SOUZA VIEIRA SILVA","Fiscal3":null,"pz_retorno":15},{"ndoc":66271,"dt_visita":"2020-06-08","tipo":"TERMO DE INTIMAÇÃO","numer":"87536","Fiscal1":"JOSE LUIZ RIBEIRO","Fiscal2":"JOSE LUIZ RIBEIRO","Fiscal3":null,"pz_retorno":0},{"ndoc":66058,"dt_visita":"2020-05-22","tipo":"TERMO DE NOTIFICAÇÃO","numer":"87493","Fiscal1":"VANESSA SANTANA","Fiscal2":"DANIEL SOARES BARBOSA","Fiscal3":"LIVIA BRITO","pz_retorno":0},{"ndoc":64219,"dt_visita":"2020-02-03","tipo":"TERMO DE INTIMAÇÃO","numer":"78097","Fiscal1":"VANESSA SANTANA","Fiscal2":"CÍCERO ANTÔNIO SIMÃO","Fiscal3":null,"pz_retorno":30},{"ndoc":48449,"dt_visita":"2014-12-01","tipo":"TERMO DE INTIMAÇÃO","numer":"39086","Fiscal1":"RÚBIA MARA DE FREITAS","Fiscal2":null,"Fiscal3":null,"pz_retorno":1},{"ndoc":48276,"dt_visita":"2014-11-25","tipo":"TERMO DE INTIMAÇÃO","numer":"38914","Fiscal1":"LUCIANA CONSOLAÇÃO DOS SANTOS","Fiscal2":"VIVIANE MANOEL DA SILVA BORGES","Fiscal3":null,"pz_retorno":15},{"ndoc":46947,"dt_visita":"2014-09-23","tipo":"TERMO DE INTIMAÇÃO","numer":"36860","Fiscal1":"LUCIANA CONSOLAÇÃO DOS SANTOS","Fiscal2":"VIVIANE MANOEL DA SILVA BORGES","Fiscal3":null,"pz_retorno":30},{"ndoc":38844,"dt_visita":"2013-10-30","tipo":"TERMO DE NOTIFICAÇÃO","numer":"31869","Fiscal1":"VIVIANE MANOEL DA SILVA BORGES","Fiscal2":"CÍCERO ANTÔNIO SIMÃO","Fiscal3":"LUCIANA CONSOLAÇÃO DOS SANTOS","pz_retorno":0},{"ndoc":38801,"dt_visita":"2013-10-29","tipo":"TERMO DE INTIMAÇÃO","numer":"31870","Fiscal1":"CÍCERO ANTÔNIO SIMÃO","Fiscal2":"LUCIANA CONSOLAÇÃO DOS SANTOS","Fiscal3":null,"pz_retorno":30},{"ndoc":35544,"dt_visita":"2013-08-02","tipo":"TERMO DE INTIMAÇÃO","numer":"29608","Fiscal1":"SIMONE DUARTE GROSSI","Fiscal2":"LUCIANA CONSOLAÇÃO DOS SANTOS","Fiscal3":null,"pz_retorno":30},{"ndoc":29456,"dt_visita":"2013-02-26","tipo":"PRORROGAÇÃO","numer":"24609","Fiscal1":"LUCIANA CONSOLAÇÃO DOS SANTOS","Fiscal2":"VIVIANE MANOEL DA SILVA BORGES","Fiscal3":null,"pz_retorno":15},{"ndoc":28724,"dt_visita":"2013-02-13","tipo":"PRORROGAÇÃO","numer":"14672","Fiscal1":"ADRIANE PEREIRA GUIMARÃES","Fiscal2":null,"Fiscal3":null,"pz_retorno":15},{"ndoc":28263,"dt_visita":"2013-02-01","tipo":"TERMO DE INTIMAÇÃO","numer":"24609","Fiscal1":"PEDRO HENRIQUE AIRES RIBEIRO","Fiscal2":"VIVIANE MANOEL DA SILVA BORGES","Fiscal3":null,"pz_retorno":15},{"ndoc":5657,"dt_visita":"2011-03-28","tipo":"TERMO DE INTIMAÇÃO","numer":"14672","Fiscal1":"DANIEL SOARES BARBOSA","Fiscal2":"LUCIANA CONSOLAÇÃO DOS SANTOS","Fiscal3":null,"pz_retorno":30}]}