{"codigo":21508,"razao":"LEILA MARIA DA SILVA BORGES","fantasia":"BIFE DE OURO","cnpj":"12.344.402/0001-92","cpf":null,"endereco":{"logradouro":"ANA JACINTA","complemento":"370","fone":null,"celular":"33112426"},"bairro":{"nome":"VILA SANTA MARIA DE NAZARETH"},"atividades":[{"subclasse":"4722-9/01","tipo":"Principal","atividade":"Comercio varejista de carnes - acougues","equipe":"AG","complexidade":"MÉDIA"}],"alvara_ultimo":{"dt_validade":"2019-10-31","exercicio":2018},"inspecoes":[{"ndoc":119840,"dt_visita":"2025-09-26","tipo":"CERTIDÃO","numer":"000000","Fiscal1":"ACADIA DE SOUZA VIEIRA SILVA","Fiscal2":null,"Fiscal3":null,"pz_retorno":0},{"ndoc":73960,"dt_visita":"2021-08-24","tipo":"PRORROGAÇÃO","numer":"86198","Fiscal1":"THIAGO GOMES GOBO","Fiscal2":null,"Fiscal3":null,"pz_retorno":5},{"ndoc":72695,"dt_visita":"2021-07-07","tipo":"TERMO DE INTIMAÇÃO","numer":"86198","Fiscal1":"ACADIA DE SOUZA VIEIRA SILVA","Fiscal2":"WANESSA DE BRITO JORGE","Fiscal3":null,"pz_retorno":45},{"ndoc":65139,"dt_visita":"2020-03-04","tipo":"TERMO DE INTIMAÇÃO","numer":"79157","Fiscal1":"GERALDO EDSON ROSA","Fiscal2":null,"Fiscal3":null,"pz_retorno":30},{"ndoc":53173,"dt_visita":"2018-10-17","tipo":"TERMO DE INTIMAÇÃO","numer":"68512","Fiscal1":"THIAGO GOMES GOBO","Fiscal2":null,"Fiscal3":null,"pz_retorno":1},{"ndoc":52088,"dt_visita":"2018-09-12","tipo":"PRORROGAÇÃO","numer":"66536","Fiscal1":"TATHIANE PESSOA DE SOUZA","Fiscal2":null,"Fiscal3":null,"pz_retorno":30},{"ndoc":51811,"dt_visita":"2018-09-05","tipo":"TERMO DE INTIMAÇÃO","numer":"66536","Fiscal1":"THIAGO GOMES GOBO","Fiscal2":null,"Fiscal3":null,"pz_retorno":7},{"ndoc":48136,"dt_visita":"2014-11-18","tipo":"PRORROGAÇÃO","numer":"38404","Fiscal1":"FABÍOLA PEDROSA PEIXOTO MARQUES","Fiscal2":"TATHIANE PESSOA DE SOUZA","Fiscal3":null,"pz_retorno":30},{"ndoc":47742,"dt_visita":"2014-11-03","tipo":"TERMO DE INTIMAÇÃO","numer":"38404","Fiscal1":"VIVIANE MANOEL DA SILVA BORGES","Fiscal2":"LUCIANA CONSOLAÇÃO DOS SANTOS","Fiscal3":null,"pz_retorno":15},{"ndoc":46291,"dt_visita":"2014-08-18","tipo":"ATO ADMINISTRATIVO DA GERÊNCIA","numer":"54745","Fiscal1":"SONIA MARIA FAUSTINO","Fiscal2":null,"Fiscal3":null,"pz_retorno":0},{"ndoc":40113,"dt_visita":"2013-12-03","tipo":"TERMO DE INTIMAÇÃO","numer":"32120","Fiscal1":"VIVIANE MANOEL DA SILVA BORGES","Fiscal2":"LUCIANA CONSOLAÇÃO DOS SANTOS","Fiscal3":null,"pz_retorno":30},{"ndoc":40115,"dt_visita":"2013-12-03","tipo":"AUTO DE INFRAÇÃO","numer":"32119","Fiscal1":"VIVIANE MANOEL DA SILVA BORGES","Fiscal2":"LUCIANA CONSOLAÇÃO DOS SANTOS","Fiscal3":null,"pz_retorno":0},{"ndoc":39898,"dt_visita":"2013-11-27","tipo":"TERMO DE INTIMAÇÃO","numer":"32110","Fiscal1":"VIVIANE MANOEL DA SILVA BORGES","Fiscal2":"LUCIANA CONSOLAÇÃO DOS SANTOS","Fiscal3":null,"pz_retorno":0},{"ndoc":38405,"dt_visita":"2013-10-15","tipo":"PRORROGAÇÃO","numer":"28231","Fiscal1":"ZEILA SILVA VILELA","Fiscal2":"CLÓVIS RAFAEL BORGES FERREIRA","Fiscal3":null,"pz_retorno":15},{"ndoc":38387,"dt_visita":"2013-10-15","tipo":"PRORROGAÇÃO","numer":"28231","Fiscal1":"CLÓVIS RAFAEL BORGES FERREIRA","Fiscal2":"ZEILA SILVA VILELA","Fiscal3":null,"pz_retorno":15},{"ndoc":38129,"dt_visita":"2013-10-07","tipo":"CERTIDÃO","numer":"00000","Fiscal1":"VIVIANE MANOEL DA SILVA BORGES","Fiscal2":"LUCIANA CONSOLAÇÃO DOS SANTOS","Fiscal3":null,"pz_retorno":0},{"ndoc":37164,"dt_visita":"2013-09-13","tipo":"PRORROGAÇÃO","numer":"28231","Fiscal1":"DAVIDMOM DA SILVA ISIDORO","Fiscal2":null,"Fiscal3":null,"pz_retorno":30},{"ndoc":35079,"dt_visita":"2013-07-16","tipo":"ATO ADMINISTRATIVO DA GERÊNCIA","numer":"26012","Fiscal1":"SONIA MARIA FAUSTINO","Fiscal2":null,"Fiscal3":null,"pz_retorno":0},{"ndoc":33579,"dt_visita":"2013-06-18","tipo":"TERMO DE INTIMAÇÃO","numer":"28231","Fiscal1":"JULIANA KÊNIA MARTINS DA SILVA","Fiscal2":"LIDIANE SIMÕES","Fiscal3":null,"pz_retorno":30},{"ndoc":33580,"dt_visita":"2013-06-18","tipo":"AUTO DE INFRAÇÃO","numer":"00296","Fiscal1":"JULIANA KÊNIA MARTINS DA SILVA","Fiscal2":"LIDIANE SIMÕES","Fiscal3":null,"pz_retorno":0},{"ndoc":27549,"dt_visita":"2013-01-14","tipo":"TERMO DE INTIMAÇÃO","numer":"21344","Fiscal1":"CLÁUDIO NASCIMENTO SILVA","Fiscal2":null,"Fiscal3":null,"pz_retorno":30}]}