{"codigo":14009,"razao":"CUNHA E SANTOS PANIFICACAO LTDA-ME","fantasia":"PAO LEVE","cnpj":"11.493.215/0001-08","cpf":null,"endereco":{"logradouro":"AV JOAO LUIZ DE OLIVEIRA","complemento":"N 202","fone":"3321-1748","celular":null},"bairro":{"nome":"SETOR ALTO DA BELA VISTA"},"atividades":[{"subclasse":"1091-1/00","tipo":"Principal","atividade":"Fabricacao de produtos de panificacao","equipe":"IA","complexidade":"ALTA"}],"alvara_ultimo":null,"inspecoes":[{"ndoc":32808,"dt_visita":"2013-05-23","tipo":"PRORROGAÇÃO","numer":"00000","Fiscal1":"ALINE CASTRO DAMASIO","Fiscal2":"LUCIENE DE SOUZA BARBOSA GOMES SILVA","Fiscal3":null,"pz_retorno":30},{"ndoc":31472,"dt_visita":"2013-04-16","tipo":"PRORROGAÇÃO","numer":"23924","Fiscal1":"GILSON REGINALDO","Fiscal2":null,"Fiscal3":null,"pz_retorno":30},{"ndoc":28680,"dt_visita":"2013-02-13","tipo":"PRORROGAÇÃO","numer":"23924","Fiscal1":"TATHIANE PESSOA DE SOUZA","Fiscal2":null,"Fiscal3":null,"pz_retorno":15},{"ndoc":28239,"dt_visita":"2013-01-31","tipo":"TERMO DE INTIMAÇÃO","numer":"23924","Fiscal1":"GÚBIO DIAS PEREIRA","Fiscal2":"VIVIANE MIYADA MACHADO","Fiscal3":null,"pz_retorno":15},{"ndoc":331,"dt_visita":"2010-07-05","tipo":"TERMO DE INTIMAÇÃO","numer":"10330","Fiscal1":"FABÍOLA PEDROSA PEIXOTO MARQUES","Fiscal2":"TATHIANE PESSOA DE SOUZA","Fiscal3":"THIAGO GOMES GOBO","pz_retorno":30},{"ndoc":2145,"dt_visita":"2010-07-05","tipo":"TERMO DE INTIMAÇÃO","numer":"10330","Fiscal1":"FABÍOLA PEDROSA PEIXOTO MARQUES","Fiscal2":"TATHIANE PESSOA DE SOUZA","Fiscal3":"THIAGO GOMES GOBO","pz_retorno":30}]}