{"codigo":14405,"razao":"MAURICE RAYNAUD FARIA","fantasia":"","cnpj":null,"cpf":"187.207.491-04","endereco":{"logradouro":"RUA ENGENHEIRO PORTELA","complemento":"Nº 151","fone":"3311-2099","celular":null},"bairro":{"nome":"CENTRO"},"atividades":[{"subclasse":"8630-5/03","tipo":"Principal","atividade":"Atividade medica ambulatorial restrita a consultas","equipe":"SS","complexidade":"MÉDIA"}],"alvara_ultimo":{"dt_validade":"2020-09-28","exercicio":2019},"inspecoes":[{"ndoc":62319,"dt_visita":"2019-11-04","tipo":"TERMO DE NOTIFICAÇÃO","numer":"76369","Fiscal1":"ARIANNE FERREIRA VIEIRA","Fiscal2":"SILVIA MARQUES NAVES DA MOTA SOUZA","Fiscal3":null,"pz_retorno":0},{"ndoc":59280,"dt_visita":"2019-07-04","tipo":"TERMO DE NOTIFICAÇÃO","numer":"74565","Fiscal1":"SIMONE DUARTE GROSSI","Fiscal2":null,"Fiscal3":null,"pz_retorno":0},{"ndoc":51994,"dt_visita":"2018-09-11","tipo":"TERMO DE NOTIFICAÇÃO","numer":"67212","Fiscal1":"ALINE CASTRO DAMASIO","Fiscal2":null,"Fiscal3":null,"pz_retorno":0},{"ndoc":43693,"dt_visita":"2014-05-21","tipo":"TERMO DE INTIMAÇÃO","numer":"34430","Fiscal1":"ZEILA SILVA VILELA","Fiscal2":null,"Fiscal3":null,"pz_retorno":30},{"ndoc":27253,"dt_visita":"2013-01-04","tipo":"TERMO DE INTIMAÇÃO","numer":"23979","Fiscal1":"ZEILA SILVA VILELA","Fiscal2":"JOÃO BATISTA LUCAS DA SILVA REIS","Fiscal3":null,"pz_retorno":30},{"ndoc":27254,"dt_visita":"2013-01-04","tipo":"AUTO DE IMPOSIÇÃO DE PENALIDADE","numer":"23980","Fiscal1":"ZEILA SILVA VILELA","Fiscal2":"JOÃO BATISTA LUCAS DA SILVA REIS","Fiscal3":null,"pz_retorno":0},{"ndoc":24113,"dt_visita":"2012-10-16","tipo":"TERMO DE INTIMAÇÃO","numer":"21476","Fiscal1":"EDSON ARANTES FARIA FILHO","Fiscal2":"ZEILA SILVA VILELA","Fiscal3":null,"pz_retorno":2},{"ndoc":21031,"dt_visita":"2012-07-10","tipo":"TERMO DE INTIMAÇÃO","numer":"01662","Fiscal1":"ZEILA SILVA VILELA","Fiscal2":null,"Fiscal3":null,"pz_retorno":30},{"ndoc":20932,"dt_visita":"2012-07-06","tipo":"TERMO DE INTIMAÇÃO","numer":"01658","Fiscal1":"ZEILA SILVA VILELA","Fiscal2":null,"Fiscal3":null,"pz_retorno":0},{"ndoc":9529,"dt_visita":"2011-08-17","tipo":"TERMO DE INTIMAÇÃO","numer":"10753","Fiscal1":"ALINE CASTRO DAMASIO","Fiscal2":"LUCIENE DE SOUZA BARBOSA GOMES SILVA","Fiscal3":null,"pz_retorno":20},{"ndoc":6749,"dt_visita":"2011-05-09","tipo":"TERMO DE NOTIFICAÇÃO","numer":"16184","Fiscal1":"ALINE CASTRO DAMASIO","Fiscal2":"LUCIENE DE SOUZA BARBOSA GOMES SILVA","Fiscal3":null,"pz_retorno":0},{"ndoc":6584,"dt_visita":"2011-05-02","tipo":"TERMO DE INTIMAÇÃO","numer":"15805","Fiscal1":"ALINE CASTRO DAMASIO","Fiscal2":"LUCIENE DE SOUZA BARBOSA GOMES SILVA","Fiscal3":"LIVIA BRITO","pz_retorno":15}]}