{"codigo":14815,"razao":"PREFEITURA MUNICIPAL DE ANAPOLIS","fantasia":"EM LAR SAO FRANCISCO DE ASSIS","cnpj":"01.067.479/0001-46","cpf":null,"endereco":{"logradouro":"RUA LARGA","complemento":"Nº 320","fone":"3902-1148","celular":null},"bairro":{"nome":"JARDIM CALIXTO"},"atividades":[{"subclasse":"8513-9/00","tipo":"Secundária","atividade":"Ensino fundamental","equipe":"ED","complexidade":"MÉDIA"},{"subclasse":"8512-1/00","tipo":"Secundária","atividade":"Educacao infantil - pre-escola","equipe":"ED","complexidade":"MÉDIA"}],"alvara_ultimo":{"dt_validade":"2025-11-25","exercicio":2024},"inspecoes":[{"ndoc":107122,"dt_visita":"2024-11-21","tipo":"TERMO DE INTIMAÇÃO","numer":"112333","Fiscal1":"VIVIANE MANOEL DA SILVA BORGES","Fiscal2":null,"Fiscal3":null,"pz_retorno":45},{"ndoc":97912,"dt_visita":"2024-03-04","tipo":"TERMO DE INTIMAÇÃO","numer":"104483","Fiscal1":"VIVIANE MANOEL DA SILVA BORGES","Fiscal2":null,"Fiscal3":null,"pz_retorno":0},{"ndoc":71167,"dt_visita":"2021-05-04","tipo":"TERMO DE INTIMAÇÃO","numer":"79542","Fiscal1":"ADRIANA CRHISTINA DE REZENDE CARNEIRO","Fiscal2":"LUCIANA CONSOLAÇÃO DOS SANTOS","Fiscal3":"VIVIANE MANOEL DA SILVA BORGES","pz_retorno":45},{"ndoc":57735,"dt_visita":"2019-04-23","tipo":"TERMO DE INTIMAÇÃO","numer":"72547","Fiscal1":"LUCIANA CONSOLAÇÃO DOS SANTOS","Fiscal2":null,"Fiscal3":null,"pz_retorno":45},{"ndoc":11573,"dt_visita":"2011-10-24","tipo":"TERMO DE INTIMAÇÃO","numer":"12527","Fiscal1":"CLÓVIS RAFAEL BORGES FERREIRA","Fiscal2":"RODRIGO ALESSANDRO TÔGO SANTOS","Fiscal3":null,"pz_retorno":30}]}