{"codigo":43229,"razao":"FINO TOK PRODUTOS DE LIMPEZA LTDA","fantasia":"FINO TOK","cnpj":"63.383.967/0001-10","cpf":null,"endereco":{"logradouro":"AV.PEDRO LUDOVICO","complemento":"QD.05, LT.11","fone":"9153-9395","celular":"(62)99153-9395"},"bairro":{"nome":"JARDIM NACOES UNIDAS"},"atividades":[{"subclasse":"4789-0/05","tipo":"Principal","atividade":"Comercio varejista de produtos saneantes domissanitarios","equipe":"CS","complexidade":"BAIXA"}],"alvara_ultimo":{"dt_validade":"2027-01-18","exercicio":2026},"inspecoes":[]}