{"codigo":43224,"razao":"DIVINO ANTONIO SANTANA","fantasia":"","cnpj":null,"cpf":"422.502.181-53","endereco":{"logradouro":"RUA MANOEL DE BASTOS","complemento":"qd 2R lt 05","fone":null,"celular":null},"bairro":{"nome":"VILA SANTA MARIA DE NAZARETH"},"atividades":[{"subclasse":"5611-2/03","tipo":"Principal","atividade":"Lanchonetes, casas de cha, de sucos e similares","equipe":"AG","complexidade":"BAIXA"}],"alvara_ultimo":null,"inspecoes":[{"ndoc":123657,"dt_visita":"2026-01-15","tipo":"TERMO DE INTIMAÇÃO","numer":"119945","pz_retorno":45}]}