{"codigo":43506,"razao":"TAVEIRA E FREGONEZI PEDIATRIA LTDA","fantasia":"AURORA & VIDA CLINICA PEDIATRICA","cnpj":"62.846.106/0001-68","cpf":null,"endereco":{"logradouro":"AVENIDA PINHEIRO CHAGAS, Nº 27","complemento":"Qd.11, Lt.50","fone":"3086-0300","celular":"(62)99550-6713"},"bairro":{"nome":"BAIRRO JUNDIAI"},"atividades":[{"subclasse":"8630-5/03","tipo":"Principal","atividade":"Atividade medica ambulatorial restrita a consultas","equipe":"SS","complexidade":"MÉDIA"},{"subclasse":"8630-5/02","tipo":"Secundária","atividade":"Atividade medica ambulatorial com recursos para realizacao de exames complementares","equipe":"SS","complexidade":"MÉDIA"}],"alvara_ultimo":null,"inspecoes":[{"ndoc":124972,"dt_visita":"2026-02-24","tipo":"TERMO DE NOTIFICAÇÃO","numer":"120548","Fiscal1":"JULIO CÉSAR TELES SPINDOLA","Fiscal2":null,"Fiscal3":null,"pz_retorno":0}]}