{"codigo":43903,"razao":"JOSE LEMES DE SOUZA FILHO","fantasia":"TICO BAR E DISTRIBUIDORA DE BEBIDAS","cnpj":"51.886.387/0001-66","cpf":null,"endereco":{"logradouro":"AV. BOA VISTA Nº 90 QD. B LT. 07","complemento":"VILA N. SRA. DOS ANJOS","fone":"9304-2166","celular":"(64)99617-9299"},"bairro":{"nome":"DISTRITO DE JOANAPOLIS"},"atividades":[{"subclasse":"5611-2/05","tipo":"Principal","atividade":"Bares e outros estabelecimentos especializados em servir bebidas com entrenimento","equipe":"AG","complexidade":"BAIXA"}],"alvara_ultimo":{"dt_validade":"2027-04-06","exercicio":2026},"inspecoes":[]}