{"codigo":12892,"razao":"GILSON VIEIRA SILVA","fantasia":"GIL GAS","cnpj":"06.979.698/0001-15","cpf":null,"endereco":{"logradouro":"RUA 34","complemento":"N 260","fone":null,"celular":null},"bairro":{"nome":"BAIRRO JK NOVA CAPITAL"},"atividades":[],"alvara_ultimo":null,"inspecoes":[{"ndoc":22788,"dt_visita":"2012-09-12","tipo":"TERMO DE INTIMAÇÃO","numer":"20025","Fiscal1":"VANESSA SANTANA","Fiscal2":"DANIELA DE ALMEIDA CASTRO","Fiscal3":null,"pz_retorno":7},{"ndoc":19152,"dt_visita":"2012-05-18","tipo":"TERMO DE INTIMAÇÃO","numer":"00526","Fiscal1":"VANESSA SANTANA","Fiscal2":"CÍCERO ANTÔNIO SIMÃO","Fiscal3":null,"pz_retorno":30},{"ndoc":14789,"dt_visita":"2012-02-02","tipo":"TERMO DE INTIMAÇÃO","numer":"14598","Fiscal1":"VANESSA SANTANA","Fiscal2":"CÍCERO ANTÔNIO SIMÃO","Fiscal3":null,"pz_retorno":30},{"ndoc":11643,"dt_visita":"2011-10-25","tipo":"TERMO DE INTIMAÇÃO","numer":"12497","Fiscal1":"CÍCERO ANTÔNIO SIMÃO","Fiscal2":null,"Fiscal3":null,"pz_retorno":30},{"ndoc":2403,"dt_visita":"2009-09-08","tipo":"TERMO DE INTIMAÇÃO","numer":"2844","Fiscal1":"CLÓVIS RAFAEL BORGES FERREIRA","Fiscal2":"RODRIGO ALESSANDRO TÔGO SANTOS","Fiscal3":null,"pz_retorno":15}]}