{"codigo":7468,"razao":"JK PRODUTOS FARMACEUTICOS LTDA","fantasia":"JK PRODUTOS FARMACEUTICOS","cnpj":"01.028.448/0001-86","cpf":null,"endereco":{"logradouro":"AV. SANTOS DUMONT","complemento":"Nº 222","fone":"3321-4477","celular":"(62)99503-4287"},"bairro":{"nome":"BAIRRO JUNDIAI"},"atividades":[{"subclasse":"4771-7/01","tipo":"Principal","atividade":"Comercio varejista de produtos farmaceuticos, sem manipulacao de formulas","equipe":"DR","complexidade":"MÉDIA"}],"alvara_ultimo":{"dt_validade":"2026-03-18","exercicio":2025},"inspecoes":[{"ndoc":114509,"dt_visita":"2025-06-05","tipo":"TERMO DE INTIMAÇÃO","numer":"116086","Fiscal1":"EDUARDO LUCAS MAGALHÃES CASTRO","Fiscal2":null,"Fiscal3":null,"pz_retorno":0},{"ndoc":110551,"dt_visita":"2025-03-18","tipo":"TERMO DE INTIMAÇÃO","numer":"114493","Fiscal1":"EDUARDO LUCAS MAGALHÃES CASTRO","Fiscal2":null,"Fiscal3":null,"pz_retorno":0},{"ndoc":99173,"dt_visita":"2024-04-11","tipo":"TERMO DE NOTIFICAÇÃO","numer":"108148","Fiscal1":"LUCIANA SANTANA DA ROCHA","Fiscal2":"KAMILLA CHRYSTINE ROLIM D. SANTOS GARCÊS","Fiscal3":null,"pz_retorno":0},{"ndoc":98338,"dt_visita":"2024-03-19","tipo":"TERMO DE INTIMAÇÃO","numer":"105250","Fiscal1":"EDUARDO LUCAS MAGALHÃES CASTRO","Fiscal2":null,"Fiscal3":null,"pz_retorno":0},{"ndoc":96961,"dt_visita":"2024-02-14","tipo":"TERMO DE INTIMAÇÃO","numer":"107805","Fiscal1":"EDSON ARANTES FARIA FILHO","Fiscal2":null,"Fiscal3":null,"pz_retorno":45},{"ndoc":86932,"dt_visita":"2023-02-16","tipo":"TERMO DE INTIMAÇÃO","numer":"097116","Fiscal1":"MARCIO HENRIQUE GOMES RODOVALHO","Fiscal2":"EDSON ARANTES FARIA FILHO","Fiscal3":null,"pz_retorno":30},{"ndoc":77374,"dt_visita":"2022-03-07","tipo":"TERMO DE NOTIFICAÇÃO","numer":"91506","Fiscal1":"EDSON ARANTES FARIA FILHO","Fiscal2":"MARCIO HENRIQUE GOMES RODOVALHO","Fiscal3":null,"pz_retorno":0},{"ndoc":77050,"dt_visita":"2022-02-21","tipo":"TERMO DE NOTIFICAÇÃO","numer":"91477","Fiscal1":"EDUARDO LUCAS MAGALHÃES CASTRO","Fiscal2":null,"Fiscal3":null,"pz_retorno":0},{"ndoc":70106,"dt_visita":"2021-02-04","tipo":"TERMO DE NOTIFICAÇÃO","numer":"83143","Fiscal1":"GLEICIANE MARIA JOSÉ DA SILVA","Fiscal2":"JULIANA FERREIRA VITURINO","Fiscal3":null,"pz_retorno":0},{"ndoc":70085,"dt_visita":"2021-02-03","tipo":"TERMO DE INTIMAÇÃO","numer":"83903","Fiscal1":"EDSON ARANTES FARIA FILHO","Fiscal2":"GLEICIANE MARIA JOSÉ DA SILVA","Fiscal3":null,"pz_retorno":30},{"ndoc":66372,"dt_visita":"2020-06-17","tipo":"TERMO DE INTIMAÇÃO","numer":"80366","Fiscal1":"JULIANA FERREIRA VITURINO","Fiscal2":"GLEICIANE MARIA JOSÉ DA SILVA","Fiscal3":null,"pz_retorno":0},{"ndoc":64179,"dt_visita":"2020-01-30","tipo":"TERMO DE INTIMAÇÃO","numer":"77360","Fiscal1":"GLEICIANE MARIA JOSÉ DA SILVA","Fiscal2":"DANIELA DE ALMEIDA CASTRO","Fiscal3":null,"pz_retorno":30},{"ndoc":55002,"dt_visita":"2019-01-08","tipo":"TERMO DE INTIMAÇÃO","numer":"70532","Fiscal1":"EDSON ARANTES FARIA FILHO","Fiscal2":null,"Fiscal3":null,"pz_retorno":30},{"ndoc":52351,"dt_visita":"2018-09-18","tipo":"TERMO DE NOTIFICAÇÃO","numer":"64645","Fiscal1":"GLEICIANE MARIA JOSÉ DA SILVA","Fiscal2":"EDSON ARANTES FARIA FILHO","Fiscal3":null,"pz_retorno":0},{"ndoc":48457,"dt_visita":"2014-10-10","tipo":"ATO ADMINISTRATIVO DA GERÊNCIA","numer":"09862","Fiscal1":"SONIA MARIA FAUSTINO","Fiscal2":null,"Fiscal3":null,"pz_retorno":0},{"ndoc":45091,"dt_visita":"2014-07-11","tipo":"TERMO DE NOTIFICAÇÃO","numer":"34513","Fiscal1":"ADRIANA CRHISTINA DE REZENDE CARNEIRO","Fiscal2":"CLÁUDIO NASCIMENTO SILVA","Fiscal3":null,"pz_retorno":0},{"ndoc":43344,"dt_visita":"2014-03-25","tipo":"TERMO DE NOTIFICAÇÃO","numer":"26544","Fiscal1":"ALINE CASTRO DAMASIO","Fiscal2":"EDSON ARANTES FARIA FILHO","Fiscal3":null,"pz_retorno":30},{"ndoc":42782,"dt_visita":"2014-03-12","tipo":"RÉPLICA FISCAL","numer":"00719","Fiscal1":"WANESSA DE BRITO JORGE","Fiscal2":"GLEICIANE MARIA JOSÉ DA SILVA","Fiscal3":null,"pz_retorno":0},{"ndoc":42002,"dt_visita":"2014-02-12","tipo":"AUTO DE INFRAÇÃO","numer":"00719","Fiscal1":"GLEICIANE MARIA JOSÉ DA SILVA","Fiscal2":"WANESSA DE BRITO JORGE","Fiscal3":null,"pz_retorno":0},{"ndoc":37396,"dt_visita":"2013-09-19","tipo":"TERMO DE INTIMAÇÃO","numer":"29652","Fiscal1":"DANIELA DE ALMEIDA CASTRO","Fiscal2":"JULIANA FERREIRA VITURINO","Fiscal3":null,"pz_retorno":0},{"ndoc":33051,"dt_visita":"2013-06-05","tipo":"TERMO DE NOTIFICAÇÃO","numer":"27958","Fiscal1":"EDSON ARANTES FARIA FILHO","Fiscal2":"GLEICIANE MARIA JOSÉ DA SILVA","Fiscal3":null,"pz_retorno":15},{"ndoc":30254,"dt_visita":"2013-03-14","tipo":"TERMO DE INTIMAÇÃO","numer":"25156","Fiscal1":"LUDIMILA PEREIRA DE ALMEIDA","Fiscal2":null,"Fiscal3":null,"pz_retorno":30},{"ndoc":24091,"dt_visita":"2012-10-16","tipo":"TERMO DE INTIMAÇÃO","numer":"20490","Fiscal1":"LUDIMILA PEREIRA DE ALMEIDA","Fiscal2":"DANIELA DE ALMEIDA CASTRO","Fiscal3":null,"pz_retorno":30},{"ndoc":16010,"dt_visita":"2012-02-28","tipo":"TERMO DE INTIMAÇÃO","numer":"15144","Fiscal1":"GLEICIANE MARIA JOSÉ DA SILVA","Fiscal2":"EDSON ARANTES FARIA FILHO","Fiscal3":null,"pz_retorno":30},{"ndoc":12670,"dt_visita":"2011-11-21","tipo":"TERMO DE NOTIFICAÇÃO","numer":"14656","Fiscal1":"GLEICIANE MARIA JOSÉ DA SILVA","Fiscal2":null,"Fiscal3":"EDSON ARANTES FARIA FILHO","pz_retorno":0},{"ndoc":11242,"dt_visita":"2011-10-14","tipo":"TERMO DE NOTIFICAÇÃO","numer":"11274","Fiscal1":"GLEICIANE MARIA JOSÉ DA SILVA","Fiscal2":"EDSON ARANTES FARIA FILHO","Fiscal3":null,"pz_retorno":30},{"ndoc":9588,"dt_visita":"2011-08-18","tipo":"TERMO DE INTIMAÇÃO","numer":"9197","Fiscal1":"GLEICIANE MARIA JOSÉ DA SILVA","Fiscal2":null,"Fiscal3":null,"pz_retorno":0},{"ndoc":7792,"dt_visita":"2011-06-22","tipo":"TERMO DE INTIMAÇÃO","numer":"16472","Fiscal1":"JULIANA FERREIRA VITURINO","Fiscal2":"LUDIMILA PEREIRA DE ALMEIDA","Fiscal3":null,"pz_retorno":0},{"ndoc":5652,"dt_visita":"2011-03-25","tipo":"TERMO DE INTIMAÇÃO","numer":"14991","Fiscal1":"GLEICIANE MARIA JOSÉ DA SILVA","Fiscal2":null,"Fiscal3":null,"pz_retorno":2},{"ndoc":5318,"dt_visita":"2011-03-14","tipo":"TERMO DE INTIMAÇÃO","numer":"14705","Fiscal1":"EDSON ARANTES FARIA FILHO","Fiscal2":"GLEICIANE MARIA JOSÉ DA SILVA","Fiscal3":null,"pz_retorno":30},{"ndoc":4524,"dt_visita":"2010-12-03","tipo":"TERMO DE NOTIFICAÇÃO","numer":"4864","Fiscal1":"LUIZ EDUARDO DUARTE MENDES","Fiscal2":null,"Fiscal3":null,"pz_retorno":0},{"ndoc":2877,"dt_visita":"2010-06-25","tipo":"TERMO DE INTIMAÇÃO","numer":"10155","Fiscal1":"EDSON ARANTES FARIA FILHO","Fiscal2":"ZEILA SILVA VILELA","Fiscal3":null,"pz_retorno":30}]}