{"codigo":16238,"razao":"RONAN GOMES DE SOUZA","fantasia":"TODA HORA LANCHE","cnpj":"13.583.744/0001-28","cpf":null,"endereco":{"logradouro":"RUA INGLATERRA","complemento":"QD. 36  LT. 18","fone":null,"celular":null},"bairro":{"nome":"BAIRRO BOA VISTA"},"atividades":[{"subclasse":"5611-2/03","tipo":"Principal","atividade":"Lanchonetes, casas de cha, de sucos e similares","equipe":"AG","complexidade":"BAIXA"}],"alvara_ultimo":null,"inspecoes":[{"ndoc":40842,"dt_visita":"2013-12-19","tipo":"TERMO DE INTIMAÇÃO","numer":"31807","Fiscal1":"DAVIDMOM DA SILVA ISIDORO","Fiscal2":null,"Fiscal3":null,"pz_retorno":0},{"ndoc":10324,"dt_visita":"2011-09-13","tipo":"TERMO DE INTIMAÇÃO","numer":"11174","Fiscal1":"LUCIANA SANTANA DA ROCHA","Fiscal2":"THIAGO GOMES GOBO","Fiscal3":null,"pz_retorno":30},{"ndoc":6151,"dt_visita":"2011-04-13","tipo":"TERMO DE INTIMAÇÃO","numer":"15504","Fiscal1":"JULIO CÉSAR TELES SPINDOLA","Fiscal2":"GERALDO EDSON ROSA","Fiscal3":null,"pz_retorno":30}]}